hough/__init__.py
hough/analyse.py
hough/cudautils.py
hough/main.py
hough/multifiles.py
hough/rotate.py
hough/stats.py
hough/utils.py
hough-0.3.1.dist-info/COPYING
hough-0.3.1.dist-info/METADATA
hough-0.3.1.dist-info/WHEEL
hough-0.3.1.dist-info/entry_points.txt
hough-0.3.1.dist-info/RECORD
