Metadata-Version: 2.3
Name: hough
Version: 0.3.1
Summary: Skew detection and correction in scanned images.
License: GPL-2.0-only
Keywords: hough,scan,rotate,deskew
Author: Joan Touzet
Author-email: wohali@apache.org
Maintainer: Joan Touzet
Maintainer-email: wohali@apache.org
Requires-Python: >=3.11,<4.0
Classifier: Development Status :: 4 - Beta
Classifier: Environment :: Console
Classifier: Intended Audience :: End Users/Desktop
Classifier: License :: OSI Approved :: GNU General Public License v2 (GPLv2)
Classifier: Operating System :: MacOS :: MacOS X
Classifier: Operating System :: Microsoft :: Windows
Classifier: Operating System :: POSIX
Classifier: Programming Language :: Python :: 3
Classifier: Programming Language :: Python :: 3.11
Classifier: Programming Language :: Python :: 3.12
Classifier: Programming Language :: Python :: 3.13
Classifier: Topic :: Multimedia :: Graphics
Classifier: Topic :: Multimedia :: Graphics :: Capture :: Scanners
Provides-Extra: cuda
Requires-Dist: cucim-cu12 (>=25.4.0) ; extra == "cuda"
Requires-Dist: cupy-cuda12x (>=13.4.1) ; extra == "cuda"
Requires-Dist: cyclopts (>=3.14.1,<4.0.0)
Requires-Dist: docopt-ng (>=0.9.0)
Requires-Dist: filetype (>=1.2.0)
Requires-Dist: imagecodecs (>=2025.3.30,<2026.0.0)
Requires-Dist: imageio (>=2.37.0)
Requires-Dist: importlib_metadata (>=6.8.0)
Requires-Dist: loguru (>=0.7.3,<0.8.0)
Requires-Dist: numpy (<2.0.0)
Requires-Dist: optuna (>=4.3.0) ; extra == "cuda"
Requires-Dist: pymupdf (>=1.23.3)
Requires-Dist: scikit-image (>=0.25.2)
Requires-Dist: scipy (>=1.15.2)
Requires-Dist: termplotlib (>=0.3.9)
Requires-Dist: tifffile (>=2025.3.30,<2026.0.0)
Requires-Dist: tqdm (>=4.66.1)
Requires-Dist: virtualenv (>=20.30.0,<21.0.0)
Project-URL: Repository, https://github.com/wohali/hough
